bareasgi_session/__init__.py
bareasgi_session/helpers.py
bareasgi_session/middleware.py
bareasgi_session/py.typed
bareasgi_session/storage/__init__.py
bareasgi_session/storage/memory_session_storage.py
bareasgi_session/storage/session_storage.py
bareasgi_session-4.0.1.dist-info/LICENSE
bareasgi_session-4.0.1.dist-info/WHEEL
bareasgi_session-4.0.1.dist-info/METADATA
bareasgi_session-4.0.1.dist-info/RECORD
