Metadata-Version: 2.1
Name: bareasgi-session
Version: 4.0.1
Summary: Session support for bareASGI
Home-page: https://github.com/rob-blackbourn/bareASGI-session
License: Apache-2.0
Keywords: bareASGI,session
Author: Rob Blackbourn
Author-email: rob.blackbourn@gmail.com
Requires-Python: >=3.8,<4.0
Classifier: License :: OSI Approved :: Apache Software License
Classifier: Programming Language :: Python :: 3
Classifier: Programming Language :: Python :: 3.8
Classifier: Programming Language :: Python :: 3.9
Requires-Dist: bareasgi (>=4.0.0,<5.0.0)
Project-URL: Repository, https://github.com/rob-blackbourn/bareASGI-session
